peacock/__init__.py
peacock/__main__.py
peacock/intercept.py
peacock-0.2.data/scripts/peacock
peacock-0.2.dist-info/DESCRIPTION.rst
peacock-0.2.dist-info/METADATA
peacock-0.2.dist-info/RECORD
peacock-0.2.dist-info/WHEEL
peacock-0.2.dist-info/metadata.json
peacock-0.2.dist-info/top_level.txt
