Metadata-Version: 2.0
Name: peacock
Version: 0.2
Summary: Peacock is Extraordinary Arbitrary Command Output Colouring Kit
Home-page: http://github.com/ztane/peacock
Author: Antti Haapala
Author-email: antti@haapala.name
License: GPLv3
Platform: UNKNOWN
